{
  "layoutContainer": {
    "layoutMode": "VERTICAL",
    "itemSpacing": 0,
    "paddingTop": 0,
    "paddingBottom": 0,
    "paddingLeft": 0,
    "paddingRight": 0,
    "primaryAxisSizingMode": "FIXED",
    "counterAxisSizingMode": "FIXED",
    "width": 375,
    "minHeight": 812
  },
  "items": [
    {
      "type": "component",
      "componentNodeId": "10:5620",
      "properties": {
        "Mode": "Light",
        "Type": "Default",
        "Elevation": "flat",
        "headline": "Used Laptops",
        "subheadline": "Find your perfect pre-owned laptop"
      }
    },
    {
      "type": "layoutContainer",
      "layoutMode": "VERTICAL",
      "itemSpacing": 16,
      "paddingTop": 16,
      "paddingBottom": 16,
      "paddingLeft": 16,
      "paddingRight": 16,
      "primaryAxisSizingMode": "AUTO",
      "counterAxisSizingMode": "AUTO",
      "horizontalSizing": "FILL",
      "layoutAlign": "STRETCH",
      "items": [
        {
          "type": "native-text",
          "properties": {
            "content": "2020 Dell XPS 13 - Excellent Condition",
            "textStyle": "Headline/Large",
            "color": "primary-500"
          }
        },
        {
          "type": "native-text",
          "properties": {
            "content": "$650",
            "textStyle": "Headline/Medium",
            "color": "primary-500"
          }
        },
        {
          "type": "layoutContainer",
          "layoutMode": "HORIZONTAL",
          "itemSpacing": 8,
          "primaryAxisSizingMode": "AUTO",
          "counterAxisSizingMode": "AUTO",
          "horizontalSizing": "FILL",
          "layoutAlign": "STRETCH",
          "items": [
            {
              "type": "native-rectangle",
              "properties": {
                "width": 100,
                "height": 100,
                "fill": {
                  "type": "IMAGE",
                  "scaleMode": "FILL"
                }
              }
            },
            {
              "type": "native-rectangle",
              "properties": {
                "width": 100,
                "height": 100,
                "fill": {
                  "type": "IMAGE",
                  "scaleMode": "FILL"
                }
              }
            },
            {
              "type": "native-rectangle",
              "properties": {
                "width": 100,
                "height": 100,
                "fill": {
                  "type": "IMAGE",
                  "scaleMode": "FILL"
                }
              }
            },
            {
              "type": "native-rectangle",
              "properties": {
                "width": 100,
                "height": 100,
                "fill": {
                  "type": "IMAGE",
                  "scaleMode": "FILL"
                }
              }
            }
          ]
        },
        {
          "type": "native-text",
          "properties": {
            "content": "Condition: Excellent (minor cosmetic scratches)",
            "textStyle": "Body/Medium",
            "color": "neutral-50"
          }
        },
        {
          "type": "layoutContainer",
          "layoutMode": "HORIZONTAL",
          "itemSpacing": 8,
          "items": [
            {
              "type": "component",
              "componentNodeId": "635:4752",
              "properties": {
                "Star": "full"
              }
            },
            {
              "type": "component",
              "componentNodeId": "635:4752",
              "properties": {
                "Star": "full"
              }
            },
            {
              "type": "component",
              "componentNodeId": "635:4752",
              "properties": {
                "Star": "full"
              }
            },
            {
              "type": "component",
              "componentNodeId": "635:4752",
              "properties": {
                "Star": "full"
              }
            },
            {
              "type": "component",
              "componentNodeId": "635:4752",
              "properties": {
                "Star": "full"
              }
            }
          ]
        },
        {
          "type": "native-text",
          "properties": {
            "content": "(150 reviews)",
            "textStyle": "Caption/Small",
            "color": "neutral-50"
          }
        },
        {
          "type": "native-text",
          "properties": {
            "content": "This 2020 Dell XPS 13 is in excellent condition and has been meticulously maintained. It features an Intel Core i5 processor, 16GB of RAM, and a 512GB SSD. Battery life is excellent, and it comes with the original charger. A few minor cosmetic scratches are present on the bottom case, but they are barely noticeable. Selling due to upgrade.",
            "textStyle": "Body/Medium",
            "color": "neutral-50"
          }
        },
        {
          "type": "layoutContainer",
          "layoutMode": "HORIZONTAL",
          "itemSpacing": 16,
          "items": [
            {
              "type": "component",
              "componentNodeId": "10:3907",
              "properties": {
                "Platform": "Android+Web",
                "Size": "Large",
                "Type": "Filled",
                "State": "Default",
                "Color": "Green",
                "Action": "Contact Seller"
              }
            },
            {
              "type": "component",
              "componentNodeId": "10:3907",
              "properties": {
                "Platform": "Android+Web",
                "Size": "Large",
                "Type": "Outlined",
                "State": "Default",
                "Color": "Green",
                "Action": "Add to Cart"
              }
            }
          ]
        }
      ]
    },
    {
      "type": "component",
      "componentNodeId": "10:4724",
      "properties": {
        "Device": "Mobile"
      }
    }
  ]
}